flask_ease/__init__.py
flask_ease/auth_schemes.py
flask_ease/exceptions.py
flask_ease/flask_ease.py
flask_ease/schemas.py
flask_ease/status.py
flask_ease/utils.py
flask_ease/templates/redoc_ui.py
flask_ease/templates/swagger_ui.py
FlaskEase-0.2.2.dist-info/LICENSE
FlaskEase-0.2.2.dist-info/METADATA
FlaskEase-0.2.2.dist-info/WHEEL
FlaskEase-0.2.2.dist-info/top_level.txt
FlaskEase-0.2.2.dist-info/RECORD
