Metadata-Version: 2.1
Name: FlaskEase
Version: 0.2.2
Summary: Flask extension for creating REST APIs. You get autogenerated OpenAPI spec (with Redoc and Swagger Docs), Request parsing and validations (query, path, body, form and files) and Response validation.
Home-page: https://github.com/zero-shubham/flask-ease
Author: Shubham Biswas
Author-email: shubhambiswas.zero@gmail.com
License: MIT
Platform: UNKNOWN
Classifier: License :: OSI Approved :: MIT License
Classifier: Programming Language :: Python :: 3
Classifier: Programming Language :: Python :: 3.8
Requires-Dist: flask (==1.1.2)
Requires-Dist: pydantic (==1.5.1)
